[
    {
        "sold_date": "Sold Oct 5, 2025",
        "listing_title": "Alkaline Trio - Goddamnit [New Vinyl LP] ALKALINE TRIO Brand New ve! Alkaline Trio Cotton Unisex Classic T Shirt S-5XL Tm \u00a2 Alkaline Trio Halloween 12\u201d X/2000 Glow In The Dark Vinyl Repress 2024 ToyGuitar - Move Like A Ghost C.D. Punk/Against Me/Dead To Me/Alkaline",
        "sold_price": "$5.66",
        "seller": null,
        "image_id": "nvdpublc76fbuybrfro6",
        "processed_at": "2025-10-07T00:17:54.872294"
    },
    {
        "sold_date": "Sold Oct 5, 2025",
        "listing_title": "AFI The Used Senses Fail Hawthorne Heights Alkaline Trio Thursday Silverstein",
        "sold_price": "$23.00",
        "seller": null,
        "image_id": "j7koyfn3wokov2asakll",
        "processed_at": "2025-10-07T00:25:02.179120"
    },
    {
        "sold_date": "Sold Oct 4, 2025",
        "listing_title": "Alkaline Trio Sticker",
        "sold_price": "$3.99",
        "seller": null,
        "image_id": "j7koyfn3wokov2asakll",
        "processed_at": "2025-10-07T00:25:02.179129"
    },
    {
        "sold_date": "Sold Oct 4, 2025",
        "listing_title": "Vintage Alkaline Trio Shirt Mens Medium Black Coffin Skull Graphic Punk Band 00s",
        "sold_price": "$59.99",
        "seller": null,
        "image_id": "j7koyfn3wokov2asakll",
        "processed_at": "2025-10-07T00:25:02.179131"
    },
    {
        "sold_date": "Sold Oct 4, 2025",
        "listing_title": "ALKALINE TRIO 2011 Original IlxI7 Concert Promo Street Poster. Portland Oregon",
        "sold_price": "$10.00",
        "seller": null,
        "image_id": "j7koyfn3wokov2asakll",
        "processed_at": "2025-10-07T00:25:02.179132"
    },
    {
        "sold_date": "Sold Oct 4, 2025",
        "listing_title": "NOFX Canvas Patch Punk Rock Emo Sew-on Badge Rancid Alkaline Trio Goth Clothing",
        "sold_price": "$2.00",
        "seller": null,
        "image_id": "j7koyfn3wokov2asakll",
        "processed_at": "2025-10-07T00:25:02.179133"
    },
    {
        "sold_date": "Sold Oct 4, 2025",
        "listing_title": "Alkaline Trio - Goddamnit CD",
        "sold_price": "$12.99",
        "seller": null,
        "image_id": "j7koyfn3wokov2asakll",
        "processed_at": "2025-10-07T00:25:02.179134"
    },
    {
        "sold_date": "Sold Oct 4, 2025",
        "listing_title": "Alkaline Trio Blue Meanies 7\u201d vinyl record Rare picture disc /1000 Bye Bye Love",
        "sold_price": "$79.99",
        "seller": null,
        "image_id": "j7koyfn3wokov2asakll",
        "processed_at": "2025-10-07T00:25:02.179138"
    },
    {
        "sold_date": "Sold Oct 3, 2025",
        "listing_title": "MATT SKIBA/ KEVIN SECONDS Split CD 2002 punk Alkaline Trio 7 Seconds & hardcore Jeet Lproduct rating Buy It Now +$6.99 delivery Sell one like this Ended Oct 3, 2025 NEW Alkaline Trio Blood, Hair, & Eyeballs Tour - Embroidered Zip-up Hoodie",
        "sold_price": "$119.99",
        "seller": null,
        "image_id": "m8p3albwvmpsdgrmbebk",
        "processed_at": "2025-10-07T00:25:10.200256"
    },
    {
        "sold_date": "Sold Oct 3, 2025",
        "listing_title": "Damnesia by Alkaline Trio (2LP Color Vinyl Never Played) Jee ikke Lproduct rating",
        "sold_price": "$15.00",
        "seller": null,
        "image_id": "m8p3albwvmpsdgrmbebk",
        "processed_at": "2025-10-07T00:25:10.200265"
    },
    {
        "sold_date": "Sold Oct 3, 2025",
        "listing_title": "ALK3 ALKALINE TRIO 2003 CINDERBLOCK GOOD MOURNING T SHIRT MENS XL FADED BAND TEE",
        "sold_price": "$69.30",
        "seller": null,
        "image_id": "m8p3albwvmpsdgrmbebk",
        "processed_at": "2025-10-07T00:25:10.200267"
    },
    {
        "sold_date": "Sold Oct 3, 2025",
        "listing_title": "Alkaline Trio Sticker",
        "sold_price": "$3.99",
        "seller": null,
        "image_id": "m8p3albwvmpsdgrmbebk",
        "processed_at": "2025-10-07T00:25:10.200268"
    },
    {
        "sold_date": "Sold Oct 3, 2025",
        "listing_title": "Is this Thing Cursed by Alkaline Trio (Record, 2018)",
        "sold_price": "$15.00",
        "seller": null,
        "image_id": "m8p3albwvmpsdgrmbebk",
        "processed_at": "2025-10-07T00:25:10.200269"
    },
    {
        "sold_date": "Sold Oct 3, 2025",
        "listing_title": "(21)\"Vans Warped Tour 2007\"-Bad Religion/Alkaline Trio/Killswitch Engage- New 2CD",
        "sold_price": "$16.11",
        "seller": null,
        "image_id": "m8p3albwvmpsdgrmbebk",
        "processed_at": "2025-10-07T00:25:10.200270"
    },
    {
        "sold_date": "Sold Oct 3, 2025",
        "listing_title": "Alkaline Trio : From Here to Infirmary CD",
        "sold_price": "$3.90",
        "seller": null,
        "image_id": "m8p3albwvmpsdgrmbebk",
        "processed_at": "2025-10-07T00:25:10.200271"
    },
    {
        "sold_date": "Sold Oct 2, 2025",
        "listing_title": "CO Not Specified (75) Alkaline Trio Car Decal Vinyl Band Logo Glossy Bumper Sticker Pop Punk see all Emo Heart Buying Format = @ Alltistings 978) $4.50 to $15.00 rockinstickers 97.8% positive (466) Buy It Now \u00a9 Avetion 190) Free delivery autre Located in United States O Accepts Offers (ese) View similar active items Sell one like this Item Location - \u00a9 vetautt Sold Oct 2, 2025 ; The Hell Sauve Les Requins White Vinyl Rare Skiba Alkaline Trio O Within 25 mi Pre-Owned \u00a9 us Only O North America $60.00 givemegrain 99.7% positive (1.8K) QO Worldwide BuyItNow Free delivery CO Arrives in 2-4 days Sell one like this CO Free Shipping \u00a9 Local Pickup within 25 mi Ended Oct 1, 2025 2008 WonkaVision calendar ~ AGAINST ME, FLOGGING MOLLY, ALKALINE show oni TRIO,more O Free Returns $6. 53 =\" ! Bi kenyatabks 99.9% positive (87.6K) \u00a9 Returns Accepted Obids CO Authorized Seller +$8.60 delivery in 2-4 days Completed Items CO Sold items CO Deals & Savings Free returns Sell one like this see all Ended Oct 1, 2025 Alkaline Trio - Remains (CD + DVD) - B-Sides and Rarities - 2007 - Vagrant Obids",
        "sold_price": "$30.65",
        "seller": null,
        "image_id": "xu9j4rmsarotnhhnx2fk",
        "processed_at": "2025-10-07T00:25:15.499598"
    },
    {
        "sold_date": "Sold Oct 1, 2025",
        "listing_title": "NEW LISTING Alkaline Trio Snapback Hat Band Tour Red Black Embroidered Rare",
        "sold_price": "$59.99",
        "seller": null,
        "image_id": "yac2u8zqpyjmszpriifs",
        "processed_at": "2025-10-07T00:25:20.544871"
    },
    {
        "sold_date": "Sold Sep 30, 2025",
        "listing_title": "Item Location 7 The Honor System - 100% Synthetic CD punk rock alkaline trio lawrence @ Detautt arms O within 25 mi Pre-Ovined \u00a9 us only CO North America Ibid \u00a9 Worldwide +$5.25 delivery Sell one like this CO Arrives in 2-4 days CO Free Shipping - Ended Sep 30, 2025 \u00a9 Local Pickup within 25 mi nofx - Sid & Nancy 7\" punk rock rancid alkaline trio bad religion lagwagon Show only - O Free ret $274.99 jeyshayza86 100% positive (IK) ree Returns on CO Retums Accepted or Best Offer +$5.00 delivery CO Authorized Seller Completed Items CO Sold items CO Deals & Savings Sell one like this see all Ended Sep 30, 2025 ALKALINE TRIO 2013 Concert Promo 11x17 Street Poster Obids",
        "sold_price": "$13.85",
        "seller": null,
        "image_id": "yac2u8zqpyjmszpriifs",
        "processed_at": "2025-10-07T00:25:20.544879"
    },
    {
        "sold_date": "Sold Sep 30, 2025",
        "listing_title": "The Honor System - 100% Synthetic CD punk rock alkaline trio lawrence arms",
        "sold_price": "$1.49",
        "seller": null,
        "image_id": "igjoe5oap7x8dlom6rvt",
        "processed_at": "2025-10-07T00:25:23.156890"
    },
    {
        "sold_date": "Sold Sep 30, 2025",
        "listing_title": "NOFX Canvas Patch Punk Rock Emo Sew-on Badge Rancid Alkaline Trio Goth Clothing",
        "sold_price": "$2.00",
        "seller": null,
        "image_id": "igjoe5oap7x8dlom6rvt",
        "processed_at": "2025-10-07T00:25:23.156899"
    },
    {
        "sold_date": "Sold Sep 30, 2025",
        "listing_title": "Rancid Canvas Patch Punk Rock Emo Sew-on Badge NOFX Alkaline Trio Goth Clothing",
        "sold_price": "$2.00",
        "seller": null,
        "image_id": "igjoe5oap7x8dlom6rvt",
        "processed_at": "2025-10-07T00:25:23.156901"
    },
    {
        "sold_date": "Sold Sep 30, 2025",
        "listing_title": "Vintage Alkaline Trio Shirt Mens XL Black 2008 Poison Bottles Band Punk Rock 00s",
        "sold_price": "$31.49",
        "seller": null,
        "image_id": "igjoe5oap7x8dlom6rvt",
        "processed_at": "2025-10-07T00:25:23.156902"
    },
    {
        "sold_date": "Sold Sep 30, 2025",
        "listing_title": "Alkaline Trio -Remains - 2007 CD/DVD Digipak - Used , Free S/H",
        "sold_price": "$21.99",
        "seller": null,
        "image_id": "igjoe5oap7x8dlom6rvt",
        "processed_at": "2025-10-07T00:25:23.156903"
    },
    {
        "sold_date": "Sold Sep 30, 2025",
        "listing_title": "From Here to Infirmary by Alkaline Trio (Record, 2023)",
        "sold_price": "$22.08",
        "seller": null,
        "image_id": "igjoe5oap7x8dlom6rvt",
        "processed_at": "2025-10-07T00:25:23.156904"
    },
    {
        "sold_date": "Sold Sep 30, 2025",
        "listing_title": "ALKALINE TRIO Band Tee Clockwork Orange Mens 2XL SHIRT RARE EMO.",
        "sold_price": "$40.00",
        "seller": null,
        "image_id": "igjoe5oap7x8dlom6rvt",
        "processed_at": "2025-10-07T00:25:23.156905"
    },
    {
        "sold_date": "Sold Sep 26, 2025",
        "listing_title": "ALKALINE TRIO - STICKER PACK",
        "sold_price": "$9.99",
        "seller": null,
        "image_id": "gi6s40rnrhxgvvhvx84z",
        "processed_at": "2025-10-07T00:25:46.650558"
    },
    {
        "sold_date": "Sold Sep 26, 2025",
        "listing_title": "Alkaline Trio Maybe I'll Catch Fire 25TH Anniversary Zoetrope Vinyl Picture Disc",
        "sold_price": "$23.50",
        "seller": null,
        "image_id": "gi6s40rnrhxgvvhvx84z",
        "processed_at": "2025-10-07T00:25:46.650566"
    },
    {
        "sold_date": "Sold Sep 26, 2025",
        "listing_title": "2008 Nike Alkaline Trio x Air Zoom Crush Premium 6.0 \u2018Heart and Soul\u2019 Pre-Owned - Nike - Nike Cush",
        "sold_price": "$500.00",
        "seller": null,
        "image_id": "gi6s40rnrhxgvvhvx84z",
        "processed_at": "2025-10-07T00:25:46.650568"
    },
    {
        "sold_date": "Sold Sep 25, 2025",
        "listing_title": "Alkaline Trio - Self-Titled CD 2000 Punk Rock Asian Man Records",
        "sold_price": "$14.87",
        "seller": null,
        "image_id": "cxk3czjltjwlrwmk9y7k",
        "processed_at": "2025-10-07T00:25:52.060734"
    },
    {
        "sold_date": "Sold Sep 25, 2025",
        "listing_title": "Alkaline Trio Past Live Williamsburg Poster 28/167",
        "sold_price": "$150.00",
        "seller": null,
        "image_id": "cxk3czjltjwlrwmk9y7k",
        "processed_at": "2025-10-07T00:25:52.060743"
    },
    {
        "sold_date": "Sold Sep 25, 2025",
        "listing_title": "Blink 182 Shirt Mens XL Black Hollywood Palladium Band Concert Alkaline Trio",
        "sold_price": "$24.99",
        "seller": null,
        "image_id": "cxk3czjltjwlrwmk9y7k",
        "processed_at": "2025-10-07T00:25:52.060744"
    },
    {
        "sold_date": "Sold Sep 25, 2025",
        "listing_title": "Kerrang! 1209 Paramore, 30 Seconds To Mars, Alkaline Trio, Glassjaw, 5 Posters ekki Loroduct rating",
        "sold_price": "$17.47",
        "seller": null,
        "image_id": "cxk3czjltjwlrwmk9y7k",
        "processed_at": "2025-10-07T00:25:52.060745"
    },
    {
        "sold_date": "Sold Sep 25, 2025",
        "listing_title": "NEW LISTING Alkaline Trio The Impossibles Fueled By Ramen Y2K Emo Shirt Accessories Lot",
        "sold_price": "$65.00",
        "seller": null,
        "image_id": "cxk3czjltjwlrwmk9y7k",
        "processed_at": "2025-10-07T00:25:52.060746"
    },
    {
        "sold_date": "Sold Sep 25, 2025",
        "listing_title": "Alkaline Trio Goth",
        "sold_price": "$2.00",
        "seller": null,
        "image_id": "cxk3czjltjwlrwmk9y7k",
        "processed_at": "2025-10-07T00:25:52.060747"
    }
]